nxfern/__init__.py
nxfern/first.py
nxfern-1.0.dist-info/METADATA
nxfern-1.0.dist-info/WHEEL
nxfern-1.0.dist-info/top_level.txt
nxfern-1.0.dist-info/RECORD
