Metadata-Version: 2.1
Name: nxfern
Version: 1.0
Summary: Demo package
Home-page: 
Author: Nicolas Fernandez
Author-email: 
License: MIT
